testpg/__init__.py
testpg/shell/__init__.py
testpg/shell/usage.py
testpg/src/__init__.py
testpg/src/demo.py
testpg-0.0.2.dist-info/LICENSE
testpg-0.0.2.dist-info/METADATA
testpg-0.0.2.dist-info/WHEEL
testpg-0.0.2.dist-info/entry_points.txt
testpg-0.0.2.dist-info/top_level.txt
testpg-0.0.2.dist-info/zip-safe
testpg-0.0.2.dist-info/RECORD
