Metadata-Version: 2.1
Name: testpg
Version: 0.0.2
Summary: your project description
Home-page: https://github.com/iunclear/python-package-template
Author: unclear
Author-email: qsykgg@gmail.com
License: MIT License
Classifier: Programming Language :: Python :: 3
Classifier: License :: OSI Approved :: MIT License
Classifier: Operating System :: OS Independent
Requires-Python: >=3.6
License-File: LICENSE
